<annotation>
	<folder>images</folder>
	<filename>20250915.072406.684.J001A1.SL.FR.JS3220.NaN.jpg</filename>
	<path>C:\Users\Safan\OneDrive\Desktop\Safan's Projects\assignment internship\part A Q1 plate recognition\images\20250915.072406.684.J001A1.SL.FR.JS3220.NaN.jpg</path>
	<source>
		<database>Unknown</database>
	</source>
	<size>
		<width>2048</width>
		<height>1600</height>
		<depth>3</depth>
	</size>
	<segmented>0</segmented>
	<object>
		<name>class1_lightVehicle</name>
		<pose>Unspecified</pose>
		<truncated>0</truncated>
		<difficult>0</difficult>
		<bndbox>
			<xmin>971</xmin>
			<ymin>593</ymin>
			<xmax>1467</xmax>
			<ymax>1156</ymax>
		</bndbox>
	</object>
	<object>
		<name>license_plate</name>
		<pose>Unspecified</pose>
		<truncated>0</truncated>
		<difficult>0</difficult>
		<bndbox>
			<xmin>1139</xmin>
			<ymin>1037</ymin>
			<xmax>1266</xmax>
			<ymax>1092</ymax>
		</bndbox>
	</object>
</annotation>
